comlid/__init__.py
comlid/__main__.py
comlid-0.0.dist-info/METADATA
comlid-0.0.dist-info/RECORD
comlid-0.0.dist-info/WHEEL
comlid-0.0.dist-info/entry_points.txt
comlid-0.0.dist-info/top_level.txt
