Metadata-Version: 2.1
Name: comlid
Version: 0.0
Summary: A Command Line based Dictionary cum Translator
Home-page: https://github.com/ayanbag/comlid
Author: Ayan Bag
Author-email: ayanbag9474@gmail.com
License: UNKNOWN
Platform: UNKNOWN
Classifier: Programming Language :: Python :: 3
Classifier: License :: OSI Approved :: MIT License
Classifier: Operating System :: OS Independent
